uFire_SHT3x/__init__.py
uFire_SHT3x/shell.py
uFire_SHT3x/uFire_SHT3x.py
uFire_SHT3x-0.9.1.dist-info/LICENSE
uFire_SHT3x-0.9.1.dist-info/METADATA
uFire_SHT3x-0.9.1.dist-info/WHEEL
uFire_SHT3x-0.9.1.dist-info/top_level.txt
uFire_SHT3x-0.9.1.dist-info/RECORD
