Metadata-Version: 2.1
Name: uFire-SHT3x
Version: 0.9.1
Summary: Measure temperature and humidity with the Sensiron SHT30 sensor.
Home-page: https://ufire.dev
Author: Microfire LLC
Author-email: contact@ufire.co
License: UNKNOWN
Project-URL: Bug Tracker, https://github.com/u-fire/uFire_SHT30/issues
Platform: UNKNOWN
Classifier: Programming Language :: Python :: 3
Classifier: License :: OSI Approved :: MIT License
Classifier: Operating System :: OS Independent
Requires-Python: >=3.6
License-File: LICENSE
